textutils_rwcrp/__init__.py
textutils_rwcrp/core.py
textutils_rwcrp-0.1.0.dist-info/licenses/LICENSE
textutils_rwcrp-0.1.0.dist-info/METADATA
textutils_rwcrp-0.1.0.dist-info/WHEEL
textutils_rwcrp-0.1.0.dist-info/top_level.txt
textutils_rwcrp-0.1.0.dist-info/RECORD
