Metadata-Version: 2.4
Name: textutils-rwcrp
Version: 0.1.0
Summary: A simple Python text utility library
Author-email: VanshShah <vanshshah@myyahoo.com>
License-Expression: MIT
Project-URL: Homepage, https://github.com/VanshMShah/PypiProject
Project-URL: Issues, https://github.com/VanshMShah/PypiProject/issues
Keywords: text,string,utils
Classifier: Programming Language :: Python :: 3
Classifier: Operating System :: OS Independent
Requires-Python: >=3.7
License-File: LICENSE
Dynamic: license-file
